[{"slug":"practicing-speaking","title":"Практика розмови","search":"практикуючи говоріння,говоріння,говоріння,виконання мовлення,виконання мовлення"},{"slug":"using-assistive-cards","title":"Використання допоміжних карток","search":"використання допоміжних карток,приклад,розмова,терапія,пропозиція"},{"slug":"planning-the-day","title":"Планування дня","search":"планування дня,використання wingo,календар,щоденне планування"},{"slug":"sleeping","title":"спить","search":"спати,час спати,спати,мріяти,котяча лапка,дрімати,відпочивати"},{"slug":"waking-up","title":"Прокидатися","search":"прокидаюся,прокидаюся,встаю,доброго ранку"},{"slug":"relaxing","title":"розслабитися","search":"розслабитися,подрімати,заспокоїтися,полежати"},{"slug":"doing-homework","title":"Робити домашнє завдання","search":"виконання домашнього завдання,навчання,виконання обов’язків,практика,самонавчання"},{"slug":"reading-book","title":"Читаючи книгу","search":"читання книг,журналів,читання коміксів,читання манги"},{"slug":"doing-outside-activities","title":"Виконання зовнішньої діяльності","search":"заняття на природі,біг,піші прогулянки,прогулянки,прийняття сонячних ванн,скелелазіння,кемпінг"},{"slug":"studying-mathematics","title":"Вивчення математики","search":"вивчення математики,навчання,математичні вправи,математичний курс"},{"slug":"brushing-teeth","title":"Чистити зуби","search":"чищення зубів,зубна щітка,підготовка до сну,стерилізація,полоскання рота"},{"slug":"preparing-school-bag","title":"Підготовка шкільний портфелик","search":"готується шкільний портфель,готується до школи,ланч-бокс"},{"slug":"taking-a-bath","title":"Приймати ванну","search":"приймати ванну,душ,ванна,приймати душ"},{"slug":"having-breakfast","title":"Снідати","search":"сніданок,рання їжа,пізній сніданок,ранкова їжа,їсти"},{"slug":"listening-to-music","title":"Слухати музику","search":"слухати музику,користуватися телефоном,смартфоном,дзвонити"},{"slug":"having-dinner","title":"Обідати","search":"обідати,їсти їжу,їсти,вечеряти"},{"slug":"playing-with-toys","title":"Гра з іграшками","search":"грати з іграшками,Барбі,машинками"},{"slug":"playing-video-games","title":"Граючи у відео ігри","search":"грати у відеоігри,xbox,playstation,nintendo,fortnite,комп'ютерна гра,консольна гра,minecraft,roblox"},{"slug":"tidy-room","title":"Охайна кімната","search":"прибирання,прибирання,пилосос"},{"slug":"watching-tv","title":"Перегляд телевізора","search":"перегляд телевізора,телебачення,серіал,перегляд фільму,документальний фільм,перегляд мультфільму,аніме"},{"slug":"having-snacks","title":"Маючи закуски","search":"закуски,шкідлива їжа,шоколад,цукерки,чіпси"},{"slug":"exercising","title":"Заняття спортом","search":"фізичні вправи,щоденні тренування,йога,біг,фітнес"},{"slug":"playing-with-friends","title":"Гра з друзями","search":"грати з друзями,гуляти з друзями,гуляти з друзями"},{"slug":"playing-ball","title":"Гра в м'яч","search":"грати в м'яч,мати 3 м'ячі,баскетбол,футбол,футбол,волейбол"},{"slug":"painting","title":"живопис","search":"живопис,мистецтво,полотно,ескіз,малюнок,розмальовка,книжка-розмальовка"},{"slug":"hanging-out-with-family","title":"Відпочинок з родиною","search":"проведення часу з сім'єю,гра з сім'єю,сімейний час"},{"slug":"riding-bicycle","title":"Їзда на велосипеді","search":"їзда на велосипеді,кататися на велосипеді,їзда на велосипеді"},{"slug":"taking-a-ride-in-the-car","title":"Покататися в машині","search":"кататися на машині,автобусі,таксі,uber"},{"slug":"swimming","title":"Плавання","search":"плавання,водні види спорту,купатися,дайвінг,пірнати"},{"slug":"drinking-juice","title":"Пити сік","search":"питний сік,питна содова вода,апельсиновий сік,смузі"},{"slug":"preparing-the-table","title":"Підготовка столу","search":"приготування столу,сервірування столу,поведінка за столом"},{"slug":"cleaning-glasses","title":"Очищення окулярів","search":"чистка окулярів,чистка окулярів"},{"slug":"shopping","title":"Шопінг","search":"шопінг,похід до торгового центру,торговий центр,торговий центр"},{"slug":"journaling","title":"Ведення журналу","search":"ведення щоденника,щоденник,календар"},{"slug":"praying","title":"Молитися","search":"молитися,ходити до церкви,молитви,мечеть,синагога"},{"slug":"dancing","title":"Танці","search":"танці,хоп,брейк-данс"},{"slug":"helping-my-mother","title":"Допомога моїй мамі","search":"допомога мамі,мамі"},{"slug":"helping-my-father","title":"Допомога моєму батькові","search":"допомагаючи батькові,батькові"},{"slug":"practicing-instruments","title":"Практичні інструменти","search":"тренування на інструментах,гітарі,піаніно,скрипці,флейті"},{"slug":"getting-dressed","title":"Одягатися","search":"одягатися,одягатися,носити одяг"},{"slug":"doctors-appointment","title":"Призначення лікаря","search":"прийом у лікаря,побачення,зустріч,призначення,побачення"},{"slug":"talking-to-therapist","title":"Розмова з терапевтом","search":"розмова з терапевтом,відвідування терапії,терапія,зустріч,призначення"},{"slug":"eating-out","title":"Харчування поза домом","search":"їсти поза домом,їсти поза домом"},{"slug":"going-to-school","title":"Ходити в школу","search":"відвідування школи,дитячого садка,ясел,дитячого садка"},{"slug":"going-to-park","title":"Йду до парку","search":"йти в парк,дитячий майданчик,ігровий майданчик"},{"slug":"singing","title":"Спів","search":"спів,караоке,співати пісню,пісню,музику"},{"slug":"going-to-cinema","title":"Ходити в кіно","search":"ходити в кіно,кіно,театр,дивитися фільм"},{"slug":"learning-code","title":"Навчальний код","search":"вивчення коду,кодування,комп'ютер"},{"slug":"drinking-milk","title":"Питне молоко","search":"пити молоко,пити"},{"slug":"playing-hopscotch","title":"Гра в класики","search":"грати hopsctoch,грати на вулиці,виходити на вулицю грати"},{"slug":"clearing-the-table","title":"Очищення столу","search":"прибирання зі столу,допомога на вечерю,приготування вечері"},{"slug":"hanging-out-with-pet","title":"Тусуватися з домашніми тваринами","search":"гуляти з домашніми тваринами,кішками,собаками,рибами,птахами"},{"slug":"doing-skincare","title":"Догляд за шкірою","search":"догляд за шкірою,обличчям,крем для обличчя,сонцезахисний крем"},{"slug":"visiting-relatives","title":"Відвідування родичів","search":"в гостях у родичів,бабусі,дідуся,бабусі,дідуся"},{"slug":"going-on-picnic","title":"Збираючись на пікнік","search":"збираємося на пікнік,барбекю,гриль,приготування їжі на вулиці,барбекю,приготування їжі"},{"slug":"making-paper-crafts","title":"Виготовлення виробів з паперу","search":"виготовлення виробів з паперу,орігамі,своїми руками"},{"slug":"taking-out-the-trash","title":"Винесення сміття","search":"вивіз сміття,сміття,сміття"},{"slug":"doing-puzzle","title":"Виконання головоломки","search":"складаючи головоломку,граючи всередині"},{"slug":"recycle","title":"Переробити","search":"переробляти,сміття,сміття,сміття"}]