[{"slug":"practicing-speaking","title":"Puhumisen harjoitteleminen","search":"harjoittelee puhumista,puhumista,puhumista,puhumista,puhumista"},{"slug":"using-assistive-cards","title":"Apukorttien käyttö","search":"käyttämällä avustavia kortteja,esimerkki,puhu,terapia,ehdota"},{"slug":"planning-the-day","title":"Päivän suunnittelu","search":"päivän suunnittelu,wingo,kalenteri,päivittäinen suunnittelu"},{"slug":"sleeping","title":"Nukkumassa","search":"nukkuminen,nukkumaanmenoaika,uni,unelma,torkut,torkut,lepo"},{"slug":"waking-up","title":"Herätä","search":"herääminen,herääminen,herääminen,hyvää huomenta"},{"slug":"relaxing","title":"rentoutua","search":"rentoutua,torkkua,rauhoittua,makuulle"},{"slug":"doing-homework","title":"Tekemässä kotitöitä","search":"läksyjä,opiskelu,velvollisuus,harjoittelu,itseopiskelu"},{"slug":"reading-book","title":"Lukea kirjaa","search":"kirjan,aikakauslehtien,sarjakuvien lukeminen,mangan lukeminen"},{"slug":"doing-outside-activities","title":"Ulkoilun tekeminen","search":"ulkoilu,juoksu,vaellus,kävely,auringonotto,kalliokiipeily,telttailu"},{"slug":"studying-mathematics","title":"Matematiikan opiskelu","search":"matematiikan opiskelu,oppiminen,matematiikan harjoittaminen,kurssimatematiikka"},{"slug":"brushing-teeth","title":"Harjata hampaita","search":"hampaiden harjaus,hammasharja,nukkumaan valmistautuminen,sterilointi,suuvesi"},{"slug":"preparing-school-bag","title":"Koululaukun valmistelu","search":"koululaukun valmistelu,kouluun valmistautuminen,lounaslaatikko"},{"slug":"taking-a-bath","title":"Kylpeä, olla kylvyssä","search":"kylvyssä,suihkussa,kylpyammeessa,suihkussa"},{"slug":"having-breakfast","title":"Syödä aamupalaa","search":"aamiaisen syöminen,aikainen ateria,brunssi,aamupala,syöminen"},{"slug":"listening-to-music","title":"Kuunnella musiikkia","search":"musiikin kuuntelu,puhelin,älypuhelin,soittaminen"},{"slug":"having-dinner","title":"Syödä päivällistä","search":"illallinen,syöminen,ruoka,päivällinen"},{"slug":"playing-with-toys","title":"Leluilla leikkiminen","search":"leikkii leluilla,barbiella,leluautoilla"},{"slug":"playing-video-games","title":"Videopelien pelaaminen","search":"pelaa videopelejä,xbox,playstation,nintendo,fortnite,tietokonepeli,konsolipeli,minecraft,roblox"},{"slug":"tidy-room","title":"Siisti huone","search":"siivoushuone,siivoushuone,imurointi"},{"slug":"watching-tv","title":"Television katsominen","search":"katsoa televisiota,televisiota,sarjoja,katsoa elokuvaa,dokumenttia,katsoa sarjakuvaa,animea"},{"slug":"having-snacks","title":"Välipaloja nauttiminen","search":"välipaloja,roskaruokaa,suklaata,karkkia,siruja"},{"slug":"exercising","title":"Harjoittelu","search":"kuntoilu,päivittäinen harjoittelu,jooga,juoksu,kuntoilu"},{"slug":"playing-with-friends","title":"Ystävien kanssa leikkiminen","search":"leikkii ystävien kanssa,mene ulos ystävien kanssa,vietä aikaa ystävien kanssa"},{"slug":"playing-ball","title":"Pallon pelaaminen","search":"pelaa palloa,on 3 palloa,koripallo,jalkapallo,jalkapallo,lentopallo"},{"slug":"painting","title":"Maalaus","search":"maalaus,taide,kangas,luonnos,piirtäminen,väritys,värityskirja"},{"slug":"hanging-out-with-family","title":"Perheen kanssa hengailua","search":"hengailu perheen kanssa,leikkiminen perheen kanssa,perheen kanssa"},{"slug":"riding-bicycle","title":"Ajaa pyörällä","search":"pyöräily,pyöräily,pyöräily"},{"slug":"taking-a-ride-in-the-car","title":"Ajelu autolla","search":"kyydissä autolla,bussilla,taksilla,uberilla"},{"slug":"swimming","title":"Uima","search":"uinti,vesiurheilu,pulahtaa,sukeltaa,sukeltaa"},{"slug":"drinking-juice","title":"Mehun juominen","search":"juomamehu,juomasooda,appelsiinimehu,smoothie"},{"slug":"preparing-the-table","title":"Taulukon valmistelu","search":"pöydän valmistelu,kattaus,pöytätavat"},{"slug":"cleaning-glasses","title":"Puhdistuslasit","search":"lasien puhdistus,silmälasien puhdistus"},{"slug":"shopping","title":"Ostokset","search":"ostoksilla,menossa ostoskeskukseen,ostoskeskukseen,ostoskeskukseen"},{"slug":"journaling","title":"Päiväkirjan kirjoittaminen","search":"päiväkirjan kirjoittaminen,päiväkirjan kirjoittaminen,kalenteri"},{"slug":"praying","title":"Rukoileminen","search":"rukoileminen,kirkossa käynti,rukous,moskeija,synagoga"},{"slug":"dancing","title":"Tanssiminen","search":"tanssi,hop,break dance"},{"slug":"helping-my-mother","title":"Auttaa äitiäni","search":"auttaa äitiäni,äitiäni"},{"slug":"helping-my-father","title":"Isäni auttaminen","search":"autan isääni,isääni"},{"slug":"practicing-instruments","title":"Harjoitteluinstrumentit","search":"harjoitussoittimet,kitara,piano,viulu,huilu"},{"slug":"getting-dressed","title":"Pukeutumassa","search":"pukeutuminen,pukeutuminen,vaatteet päällä"},{"slug":"doctors-appointment","title":"Lääkärin vastaanotto","search":"lääkärin vastaanotto,päivämäärä,tapaaminen,tapaaminen,tapaaminen"},{"slug":"talking-to-therapist","title":"Keskustele terapeutin kanssa","search":"puhuminen terapeutin kanssa,terapiassa käyminen,terapia,tapaaminen,tapaaminen"},{"slug":"eating-out","title":"Syödä ulkona","search":"ulkona syöminen,ulkona syöminen"},{"slug":"going-to-school","title":"Menee kouluun","search":"menossa kouluun,päiväkotiin,päiväkotiin,päiväkotiin,päiväkotiin"},{"slug":"going-to-park","title":"Puistoon menossa","search":"menossa puistoon,leikkikentälle,leikkialueelle"},{"slug":"singing","title":"Laulaminen","search":"laulaa,karaokea,laulaa laulua,laulua,musiikkia"},{"slug":"going-to-cinema","title":"Elokuvateatteriin menossa","search":"menossa elokuviin,elokuvaan,teatteriin,katsomassa elokuvaa"},{"slug":"learning-code","title":"Oppimiskoodi","search":"oppimiskoodi,koodaus,tietokone"},{"slug":"drinking-milk","title":"Maidon juominen","search":"juo maitoa,juo"},{"slug":"playing-hopscotch","title":"Pelaa Hopscotchia","search":"pelata hopsctochia,leikkiä ulkona,mennä ulos leikkimään"},{"slug":"clearing-the-table","title":"Pöydän tyhjentäminen","search":"pöydän siivoaminen,apu päivälliselle,illallisen valmistaminen"},{"slug":"hanging-out-with-pet","title":"Lemmikin kanssa hengailua","search":"viettää aikaa lemmikin,kissan,koiran,kalan,linnun kanssa"},{"slug":"doing-skincare","title":"Ihonhoitoa tekemässä","search":"tekee ihonhoitoa,kasvohoitoa,kasvovoidetta,aurinkovoidetta"},{"slug":"visiting-relatives","title":"Vierailla sukulaisilla","search":"vierailemassa sukulaisten,isoäidin,isoisän,isoäidin,isoisän luona"},{"slug":"going-on-picnic","title":"Piknikille menossa","search":"menossa piknikille,BBQ,grilli,ruoanlaitto ulkona,grillaus,ruoanlaitto"},{"slug":"making-paper-crafts","title":"Paperikäsitöiden tekeminen","search":"paperikäsitöiden tekeminen,origami,itse tekeminen"},{"slug":"taking-out-the-trash","title":"Viedä roskat ulos","search":"viedä roskat,roskat,roskat"},{"slug":"doing-puzzle","title":"Puzzlea tekemässä","search":"tekee pulmia,leikkii sisällä"},{"slug":"recycle","title":"Kierrättää","search":"kierrättää,roskat,roskat,roskat"}]