[{"slug":"cotton-candy","title":"Wata cukrowa","phrases":[{"type":"❤️","phrase":"Lubię jeść watę cukrową."}]},{"slug":"magic-hat","title":"Magiczny kapelusz","phrases":[{"type":"❤️","phrase":"Lubię nosić magiczny kapelusz."}]},{"slug":"ferris-wheel","title":"diabelski młyn","phrases":[{"type":"❤️","phrase":"Lubię jeździć na diabelskim młynie."}]},{"slug":"bowling","title":"Kręgle","phrases":[{"type":"❤️","phrase":"Lubię grać w kręgle."}]},{"slug":"bumper-car","title":"Samochód zderzak","phrases":[{"type":"❤️","phrase":"Lubię jeździć w zderzaku."}]},{"slug":"carousel","title":"Karuzela","phrases":[{"type":"❤️","phrase":"Lubię jeździć na karuzeli."}]},{"slug":"balloons","title":"Balony","phrases":[{"type":"❤️","phrase":"Lubię balony."}]},{"slug":"cups","title":"Kubki","phrases":[{"type":"❤️","phrase":"Lubię pić z kubków."}]},{"slug":"unicycle","title":"monocykl","phrases":[{"type":"❤️","phrase":"Lubię jeździć na monocyklu."}]},{"slug":"circus-tent","title":"Namiot cyrkowy","phrases":[{"type":"❤️","phrase":"Lubię zwiedzać w namiocie cyrkowym."}]},{"slug":"food-truck","title":"Ciężarówka z żywnością","phrases":[{"type":"❤️","phrase":"Lubię dostawać jedzenie z food trucka."}]},{"slug":"tea-cup-ride","title":"Przejażdżka po filiżance herbaty","phrases":[{"type":"❤️","phrase":"Lubię kręcić się w przejażdżce po filiżance herbaty."}]},{"slug":"whack-a-mole","title":"Uderz kreta","phrases":[{"type":"❤️","phrase":"Lubię bawić się w walenie kreta."}]},{"slug":"food-stall","title":"Stoisko żywności","phrases":[{"type":"❤️","phrase":"Lubię próbować nowych potraw ze straganu z jedzeniem."}]},{"slug":"claw-machine","title":"Maszyna pazurów","phrases":[{"type":"❤️","phrase":"Lubię próbować wygrać nagrodę z maszyny z pazurami."}]},{"slug":"shooting-target","title":"Strzelanie do celu","phrases":[{"type":"❤️","phrase":"Lubię strzelać do celu."}]},{"slug":"teddy-bear","title":"Miś","phrases":[{"type":"❤️","phrase":"Lubię przytulać pluszowego misia."}]},{"slug":"fireworks","title":"Fajerwerki","phrases":[{"type":"❤️","phrase":"Lubię oglądać fajerwerki."}]},{"slug":"caramelized-apple","title":"karmelizowane jabłko","phrases":[{"type":"❤️","phrase":"Lubię jeść karmelizowane jabłka."}]},{"slug":"ring","title":"Pierścień","phrases":[{"type":"❤️","phrase":"Lubię nosić pierścionek."}]}]