[{"slug":"walking","title":"ウォーキング","phrases":[{"type":"❤️","phrase":"散歩が好き"},{"type":"❌","phrase":"私は歩くのが好きではない"},{"type":"🙋","phrase":"一緒に歩きませんか？"}]},{"slug":"running","title":"ランニング","phrases":[{"type":"❤️","phrase":"走るのが好きです。"},{"type":"❌","phrase":"私は走るのが好きではありません。"},{"type":"🙋","phrase":"走りに行きたいですか？"}]},{"slug":"talking","title":"おしゃべり","phrases":[{"type":"❤️","phrase":"私は話すのが好きです。"},{"type":"❌","phrase":"私は話すのが好きではありません。"},{"type":"🙋","phrase":"あなたは私と話をしたいですか？"}]},{"slug":"reading","title":"読む","phrases":[{"type":"❤️","phrase":"私は読書が好きです。"},{"type":"❌","phrase":"私は読書が好きではありません。"},{"type":"🙋","phrase":"一緒に読みませんか？"}]},{"slug":"football","title":"フットボール","phrases":[{"type":"❤️","phrase":"私はサッカーをするのが好きです。"},{"type":"❌","phrase":"私はサッカーをするのが好きではありません。"},{"type":"🙋","phrase":"サッカーをしたいですか？"}]},{"slug":"basketball","title":"バスケットボール","phrases":[{"type":"❤️","phrase":"私はバスケットボールをするのが好きです。"},{"type":"❌","phrase":"私はバスケットボールをするのが好きではありません。"},{"type":"🙋","phrase":"バスケットボールをしたいですか？"}]},{"slug":"swimming","title":"水泳","phrases":[{"type":"❤️","phrase":"私は水泳が好きです。"},{"type":"❌","phrase":"私は水泳が好きではありません。"},{"type":"🙋","phrase":"水泳に行きたいですか。"}]},{"slug":"painting","title":"ペインティング","phrases":[{"type":"❤️","phrase":"私は絵が好きです。"},{"type":"❌","phrase":"私は絵を描くのが好きではありません。"},{"type":"🙋","phrase":"一緒に絵を描きませんか？"}]},{"slug":"drawing","title":"描く","phrases":[{"type":"❤️","phrase":"私は絵を描くのが好きです。"},{"type":"❌","phrase":"私は絵を描くのが好きではありません。"},{"type":"🙋","phrase":"一緒に描きませんか？"}]},{"slug":"cycling","title":"サイクリング","phrases":[{"type":"❤️","phrase":"私はサイクリングが好きです。"},{"type":"❌","phrase":"私はサイクリングが好きではありません。"},{"type":"🙋","phrase":"サイクリングに行きたいですか？"}]},{"slug":"skating","title":"スケート","phrases":[{"type":"❤️","phrase":"私はスケートが好きです。"},{"type":"❌","phrase":"私はスケートが好きではありません。"},{"type":"🙋","phrase":"スケートに行きたいですか？"}]},{"slug":"sightseeing","title":"観光","phrases":[{"type":"❤️","phrase":"私は観光が好きです。"},{"type":"❌","phrase":"私は観光が好きではありません。"},{"type":"🙋","phrase":"観光に行きませんか？"}]},{"slug":"video-games","title":"ビデオゲーム","phrases":[{"type":"❤️","phrase":"私はビデオゲームをするのが好きです。"},{"type":"❌","phrase":"私はビデオゲームをするのが好きではありません。"},{"type":"🙋","phrase":"ゲームをしたいですか？"}]},{"slug":"tidying","title":"片付け","phrases":[{"type":"❤️","phrase":"私は自分の部屋を片付けるのが好きです。"},{"type":"❌","phrase":"私は自分の部屋を片付けるのが好きではありません。"},{"type":"🙋","phrase":"私の部屋を片付けるのを手伝ってくれませんか?"}]},{"slug":"toys","title":"おもちゃ","phrases":[{"type":"❤️","phrase":"私はおもちゃが好きです。"},{"type":"❌","phrase":"私はおもちゃが好きではありません。"},{"type":"🙋","phrase":"私のおもちゃで遊びませんか？"}]},{"slug":"puzzle","title":"パズル","phrases":[{"type":"❤️","phrase":"パズルを解くのが好きです。"},{"type":"❌","phrase":"私はパズルを解くのが好きではありません。"},{"type":"🙋","phrase":"私と一緒にパズルを解きませんか？"}]},{"slug":"comics","title":"漫画","phrases":[{"type":"❤️","phrase":"私は漫画を読むのが好きです。"},{"type":"❌","phrase":"私は漫画を読むのが苦手です。"},{"type":"🙋","phrase":"漫画を読みたいですか？"}]},{"slug":"chess","title":"チェス","phrases":[{"type":"❤️","phrase":"私はチェスをするのが好きです。"},{"type":"❌","phrase":"私はチェスをするのが好きではありません。"},{"type":"🙋","phrase":"私とチェスをしませんか？"}]},{"slug":"using-leeloo","title":"リールーの使い方","phrases":[{"type":"❤️","phrase":"私はleelooを使うのが好きです。"},{"type":"❌","phrase":"私はleelooを使うのが好きではありません。"},{"type":"🙋","phrase":"leelooでカードパックを変更できますか？"}]},{"slug":"texting","title":"テキストメッセージ","phrases":[{"type":"❤️","phrase":"私はテキストメッセージが好きです。"},{"type":"❌","phrase":"私はテキストメッセージが好きではありません。"}]},{"slug":"knitting","title":"編み物","phrases":[{"type":"❤️","phrase":"私は編み物が好きです。"},{"type":"❌","phrase":"私は編み物が好きではありません。"},{"type":"🙋","phrase":"編み物を習いたいです。"}]},{"slug":"bowling","title":"ボウリング","phrases":[{"type":"❤️","phrase":"私はボウリングが好きです。"},{"type":"❌","phrase":"私はボウリングが好きではありません。"},{"type":"🙋","phrase":"一緒にボーリングしませんか？"}]},{"slug":"watching-tv","title":"テレビを見ている","phrases":[{"type":"❤️","phrase":"私はテレビを見るのが好きです。"},{"type":"❌","phrase":"私はテレビを見るのが好きではありません。"},{"type":"🙋","phrase":"テレビを見たいですか？"}]},{"slug":"fishing","title":"釣り","phrases":[{"type":"❤️","phrase":"私は釣りが好きです。"},{"type":"❌","phrase":"私は釣りが好きではありません。"},{"type":"🙋","phrase":"釣りに行きませんか？"}]},{"slug":"exercising","title":"運動する","phrases":[{"type":"❤️","phrase":"私は運動するのが好きです。"},{"type":"❌","phrase":"私は運動するのが好きではありません。"},{"type":"🙋","phrase":"私と一緒に運動しませんか？"}]},{"slug":"tennis","title":"テニス","phrases":[{"type":"❤️","phrase":"私はテニスをするのが好きです。"},{"type":"❌","phrase":"私はテニスをするのが好きではありません。"},{"type":"🙋","phrase":"私と一緒にテニスをしませんか。"}]}]