[{"slug":"water-bottle","title":"پانی کی بوتل","phrases":[{"type":"✔️","phrase":"میرے پاس پانی کی بوتل ہے۔"},{"type":"❌","phrase":"میرے پاس پانی کی بوتل نہیں ہے۔"},{"type":"🙋","phrase":"کیا آپ کے پاس پانی کی بوتل ہے؟"}]},{"slug":"tea-cup","title":"کپ","phrases":[{"type":"✔️","phrase":"میرے پاس ایک کپ ہے۔"},{"type":"❌","phrase":"میرے پاس کپ نہیں ہے۔"},{"type":"🙋","phrase":"کیا آپ کے پاس کپ ہے؟"}]},{"slug":"coffee-cup","title":"کافی کپ","phrases":[{"type":"✔️","phrase":"میرے پاس کافی کا کپ ہے۔"},{"type":"❌","phrase":"میرے پاس کافی کا کپ نہیں ہے۔"},{"type":"🙋","phrase":"کیا آپ کے پاس کافی کا کپ ہے؟"}]},{"slug":"keyboard","title":"کی بورڈ","phrases":[{"type":"✔️","phrase":"میرے پاس کی بورڈ ہے۔"},{"type":"❌","phrase":"میرے پاس کی بورڈ نہیں ہے۔"},{"type":"🙋","phrase":"کیا آپ کے پاس کی بورڈ ہے؟"}]},{"slug":"computer","title":"کمپیوٹر","phrases":[{"type":"✔️","phrase":"میرے پاس کمپیوٹر ہے۔"},{"type":"❌","phrase":"میرے پاس کمپیوٹر نہیں ہے۔"},{"type":"🙋","phrase":"کیا اپ کے پاس کمپیوٹر ہے؟"}]},{"slug":"monitor","title":"مانیٹر","phrases":[{"type":"✔️","phrase":"میرے پاس مانیٹر ہے۔"},{"type":"❌","phrase":"میرے پاس مانیٹر نہیں ہے۔"},{"type":"🙋","phrase":"کیا آپ کے پاس مانیٹر ہے؟"}]},{"slug":"joystick","title":"جوائس اسٹک","phrases":[{"type":"✔️","phrase":"میرے پاس جوائس اسٹک ہے۔"},{"type":"❌","phrase":"میرے پاس جوائس اسٹک نہیں ہے۔"},{"type":"🙋","phrase":"کیا آپ کے پاس جوائس اسٹک ہے؟"}]},{"slug":"pencil","title":"پینسل","phrases":[{"type":"✔️","phrase":"میرے پاس پنسل ہے۔"},{"type":"❌","phrase":"میرے پاس پنسل نہیں ہے۔"},{"type":"🙋","phrase":"کیا آپ کے پاس پنسل ہے؟"}]},{"slug":"eraser","title":"صاف کرنے والا","phrases":[{"type":"✔️","phrase":"میرے پاس ایک صافی ہے۔"},{"type":"❌","phrase":"میرے پاس صافی نہیں ہے۔"},{"type":"🙋","phrase":"کیا آپ کے پاس صافی ہے؟"}]},{"slug":"sharpener","title":"تیز کرنے والا","phrases":[{"type":"✔️","phrase":"میرے پاس شارپنر ہے۔"},{"type":"❌","phrase":"میرے پاس شارپنر نہیں ہے۔"},{"type":"🙋","phrase":"کیا آپ کے پاس شارپنر ہے؟"}]},{"slug":"fan","title":"پنکھا","phrases":[{"type":"✔️","phrase":"میرے پاس ایک پنکھا ہے۔"},{"type":"❌","phrase":"میرے پاس پنکھا نہیں ہے۔"},{"type":"🙋","phrase":"کیا آپ کے پاس پنکھا ہے؟"}]},{"slug":"airconditioner","title":"اے سی","phrases":[{"type":"✔️","phrase":"میرے پاس ایئر کنڈیشنر ہے۔"},{"type":"❌","phrase":"میرے پاس ایئر کنڈیشنر نہیں ہے۔"},{"type":"🙋","phrase":"کیا آپ کے پاس ایئر کنڈیشنر ہے؟"}]},{"slug":"cellphone","title":"موبائل فون","phrases":[{"type":"✔️","phrase":"میرے پاس سیل فون ہے۔"},{"type":"❌","phrase":"میرے پاس سیل فون نہیں ہے۔"},{"type":"🙋","phrase":"کیا اپ کے پاس سیل فون ہے؟"}]},{"slug":"backpack","title":"بیگ","phrases":[{"type":"✔️","phrase":"میرے پاس ایک بیگ ہے۔"},{"type":"❌","phrase":"میرے پاس بیگ نہیں ہے۔"},{"type":"🙋","phrase":"کیا آپ کے پاس ایک بیگ ہے؟"}]},{"slug":"chair","title":"کرسی","phrases":[{"type":"✔️","phrase":"میرے پاس ایک کرسی ہے۔"},{"type":"❌","phrase":"میرے پاس کرسی نہیں ہے۔"},{"type":"🙋","phrase":"کیا آپ کے پاس کرسی ہے؟"}]},{"slug":"teapot","title":"چائے کا برتن","phrases":[{"type":"✔️","phrase":"میرے پاس ایک چائے والا ہے۔"},{"type":"❌","phrase":"میرے پاس چائے کا برتن نہیں ہے۔"},{"type":"🙋","phrase":"کیا آپ کے پاس چائے کا برتن ہے؟"}]},{"slug":"soap-dispenser","title":"صابن دان","phrases":[{"type":"✔️","phrase":"میرے پاس صابن کا ڈسپنسر ہے۔"},{"type":"❌","phrase":"میرے پاس صابن ڈسپنسر نہیں ہے۔"},{"type":"🙋","phrase":"کیا آپ کے پاس صابن ڈسپنسر ہے؟"}]},{"slug":"sock","title":"جراب","phrases":[{"type":"✔️","phrase":"میرے پاس ایک جراب ہے۔"},{"type":"❌","phrase":"میرے پاس جراب نہیں ہے۔"},{"type":"🙋","phrase":"کیا آپ کے پاس جراب ہے؟"}]},{"slug":"desk","title":"ڈیسک","phrases":[{"type":"✔️","phrase":"میرے پاس ایک میز ہے۔"},{"type":"❌","phrase":"میرے پاس ڈیسک نہیں ہے۔"},{"type":"🙋","phrase":"کیا آپ کے پاس میز ہے؟"}]},{"slug":"printer","title":"پرنٹر","phrases":[{"type":"✔️","phrase":"میرے پاس ایک پرنٹر ہے۔"},{"type":"❌","phrase":"میرے پاس پرنٹر نہیں ہے۔"},{"type":"🙋","phrase":"کیا آپ کے پاس پرنٹر ہے؟"}]},{"slug":"stove","title":"چولہا۔","phrases":[{"type":"✔️","phrase":"میرے پاس چولہا ہے۔"},{"type":"❌","phrase":"میرے پاس چولہا نہیں ہے۔"},{"type":"🙋","phrase":"کیا آپ کے پاس چولہا ہے؟"}]},{"slug":"frying-pan","title":"کڑاہی","phrases":[{"type":"✔️","phrase":"میرے پاس کڑاہی ہے۔"},{"type":"❌","phrase":"میرے پاس کڑاہی نہیں ہے۔"},{"type":"🙋","phrase":"کیا آپ کے پاس کڑاہی ہے؟"}]},{"slug":"bed","title":"بستر","phrases":[{"type":"✔️","phrase":"میرے پاس ایک بستر ہے۔"},{"type":"❌","phrase":"میرے پاس بستر نہیں ہے۔"},{"type":"🙋","phrase":"کیا آپ کے پاس بستر ہے؟"}]},{"slug":"paper-towel","title":"کاغذی تولیہ","phrases":[{"type":"✔️","phrase":"میرے پاس کاغذ کا تولیہ ہے۔"},{"type":"❌","phrase":"میرے پاس کاغذ کا تولیہ نہیں ہے۔"},{"type":"🙋","phrase":"کیا آپ کے پاس کاغذ کا تولیہ ہے؟"}]},{"slug":"curtain","title":"پردے","phrases":[{"type":"✔️","phrase":"میرے پاس پردہ ہے۔"},{"type":"❌","phrase":"میرے پاس پردہ نہیں ہے۔"},{"type":"🙋","phrase":"کیا آپ کے پاس پردہ ہے؟"}]},{"slug":"couch","title":"صوفہ","phrases":[{"type":"✔️","phrase":"میرے پاس ایک صوفہ ہے۔"},{"type":"❌","phrase":"میرے پاس صوفہ نہیں ہے۔"},{"type":"🙋","phrase":"کیا آپ کے پاس صوفہ ہے؟"}]},{"slug":"ruler","title":"حکمران","phrases":[{"type":"✔️","phrase":"میرے پاس ایک حکمران ہے۔"},{"type":"❌","phrase":"میرے پاس کوئی حکمران نہیں ہے۔"},{"type":"🙋","phrase":"کیا آپ کے پاس کوئی حکمران ہے؟"}]},{"slug":"wardrobe","title":"الماری","phrases":[{"type":"✔️","phrase":"میرے پاس الماری ہے۔"},{"type":"❌","phrase":"میرے پاس الماری نہیں ہے۔"},{"type":"🙋","phrase":"کیا آپ کے پاس الماری ہے؟"}]},{"slug":"rug","title":"قالین","phrases":[{"type":"✔️","phrase":"میرے پاس ایک قالین ہے۔"},{"type":"❌","phrase":"میرے پاس قالین نہیں ہے۔"},{"type":"🙋","phrase":"کیا آپ کے پاس قالین ہے؟"}]},{"slug":"toaster","title":"ٹوسٹر","phrases":[{"type":"✔️","phrase":"میرے پاس ٹوسٹر ہے۔"},{"type":"❌","phrase":"میرے پاس ٹوسٹر نہیں ہے۔"},{"type":"🙋","phrase":"کیا آپ کے پاس ٹوسٹر ہے؟"}]},{"slug":"scale","title":"پیمانہ","phrases":[{"type":"✔️","phrase":"میرے پاس ایک پیمانہ ہے۔"},{"type":"❌","phrase":"میرے پاس پیمانہ نہیں ہے۔"},{"type":"🙋","phrase":"کیا آپ کے پاس پیمانہ ہے؟"}]},{"slug":"remote-control","title":"ریموٹ کنٹرول","phrases":[{"type":"✔️","phrase":"میرے پاس ریموٹ کنٹرول ہے۔"},{"type":"❌","phrase":"میرے پاس ریموٹ کنٹرول نہیں ہے۔"},{"type":"🙋","phrase":"کیا آپ کے پاس ریموٹ کنٹرول ہے؟"}]},{"slug":"trash-bin","title":"ردی کی ٹوکری","phrases":[{"type":"✔️","phrase":"میرے پاس ردی کی ٹوکری ہے۔"},{"type":"❌","phrase":"میرے پاس ردی کی ٹوکری نہیں ہے۔"},{"type":"🙋","phrase":"کیا آپ کے پاس ردی کی ٹوکری ہے؟"}]},{"slug":"plastic-bag","title":"پلاسٹک بیگ","phrases":[{"type":"✔️","phrase":"میرے پاس پلاسٹک کا بیگ ہے۔"},{"type":"❌","phrase":"میرے پاس پلاسٹک کا بیگ نہیں ہے۔"},{"type":"🙋","phrase":"کیا آپ کے پاس پلاسٹک کا بیگ ہے؟"}]},{"slug":"laptop","title":"لیپ ٹاپ","phrases":[{"type":"✔️","phrase":"میرے پاس لیپ ٹاپ ہے۔"},{"type":"❌","phrase":"میرے پاس لیپ ٹاپ نہیں ہے۔"},{"type":"🙋","phrase":"کیا آپ کے پاس لیپ ٹاپ ہے؟"}]},{"slug":"pillow","title":"تکیہ","phrases":[{"type":"✔️","phrase":"میرے پاس تکیہ ہے۔"},{"type":"❌","phrase":"میرے پاس تکیہ نہیں ہے۔"},{"type":"🙋","phrase":"کیا آپ کے پاس تکیہ ہے؟"}]},{"slug":"coffee-mug","title":"کافی کا مگ","phrases":[{"type":"✔️","phrase":"میرے پاس کافی کا مگ ہے۔"},{"type":"❌","phrase":"میرے پاس کافی کا مگ نہیں ہے۔"},{"type":"🙋","phrase":"کیا آپ کے پاس کافی کا مگ ہے؟"}]},{"slug":"lamp","title":"چراغ","phrases":[{"type":"✔️","phrase":"میرے پاس ایک چراغ ہے۔"},{"type":"❌","phrase":"میرے پاس چراغ نہیں ہے۔"},{"type":"🙋","phrase":"کیا آپ کے پاس چراغ ہے؟"}]},{"slug":"bookshelf","title":"بک شیلف","phrases":[{"type":"✔️","phrase":"میرے پاس کتابوں کی الماری ہے۔"},{"type":"❌","phrase":"میرے پاس کتابوں کی الماری نہیں ہے۔"},{"type":"🙋","phrase":"کیا آپ کے پاس کتابوں کی الماری ہے؟"}]},{"slug":"pencil-case","title":"پنسل کیس","phrases":[{"type":"✔️","phrase":"میرے پاس پنسل کیس ہے۔"},{"type":"❌","phrase":"میرے پاس پنسل کیس نہیں ہے۔"},{"type":"🙋","phrase":"کیا آپ کے پاس پنسل کیس ہے؟"}]},{"slug":"plant","title":"پودا","phrases":[{"type":"✔️","phrase":"میرے پاس ایک پودا ہے۔"},{"type":"❌","phrase":"میرے پاس پودا نہیں ہے۔"},{"type":"🙋","phrase":"کیا آپ کے پاس پودا ہے؟"}]}]