[{"slug":"practicing-speaking","title":"Precvičovanie rozprávania","search":"precvičovanie rozprávania,rozprávanie,rozprávanie,predvádzanie rozprávania,robenie rozprávania"},{"slug":"using-assistive-cards","title":"Používanie asistenčných kariet","search":"pomocou pomocných kariet,príklad,hovor,terapia,navrhnutie"},{"slug":"planning-the-day","title":"Plánovanie dňa","search":"plánovanie dňa,pomocou winga,kalendára,denného plánovania"},{"slug":"sleeping","title":"Spanie","search":"spánok,čas v posteli,spánok,snívanie,driemanie,driemanie,oddych"},{"slug":"waking-up","title":"Zobúdzať sa","search":"vstávanie,prebúdzanie,vstávanie,dobré ráno"},{"slug":"relax","title":"relaxovať","search":"relaxovať,driemať,upokojovať sa,ľahnúť si"},{"slug":"doing-homework","title":"Robiť si domáce úlohy","search":"robenie domácich úloh,štúdium,plnenie povinností,cvičenie,samoštúdium"},{"slug":"reading-book","title":"Čítanie knihy","search":"čítanie kníh,časopisov,čítanie komiksov,čítanie mangy"},{"slug":"doing-outside-activities","title":"Vykonávanie vonkajších aktivít","search":"vonkajšie aktivity,beh,turistika,chôdza,opaľovanie,horolezectvo,kempovanie"},{"slug":"studying-mathematics","title":"Štúdium matematiky","search":"štúdium matematiky,učenie,cvičebná matematika,kurz matematiky"},{"slug":"brushing-teeth","title":"Umývanie zubov","search":"čistenie zubov,zubná kefka,príprava na spánok,sterilizácia,ústna voda"},{"slug":"preparing-school-bag","title":"Príprava školskej tašky","search":"príprava školskej tašky,príprava do školy,obedár"},{"slug":"taking-a-bath","title":"Kúpať sa","search":"kúpanie,sprchovanie,vaňa,sprchovanie"},{"slug":"having-breakfast","title":"Raňajkovať","search":"raňajky,skoré jedlo,neskoré raňajky,ranné jedlo,jesť"},{"slug":"listening-to-music","title":"Počúvanie hudby","search":"počúvanie hudby,používanie telefónu,smartfónu,volanie"},{"slug":"having-dinner","title":"Večera","search":"mať večeru,jesť jedlo,jedlo,jesť večeru"},{"slug":"playing-with-toys","title":"Hranie sa s hračkami","search":"hrať sa s hračkami,Barbie,autíčkami"},{"slug":"playing-video-games","title":"Hranie videohier","search":"hranie videohier,xbox,playstation,nintendo,fortnite,počítačová hra,hra na konzolu,minecraft,roblox"},{"slug":"tidy-room","title":"Uprataná izba","search":"upratovacia miestnosť,upratovačka,vysávanie"},{"slug":"watching-tv","title":"Pozeranie TV","search":"sledovanie televízie,televízie,seriálu,sledovanie filmu,dokumentu,sledovanie karikatúry,anime"},{"slug":"having-snacks","title":"Občerstvenie","search":"s občerstvením,nezdravým jedlom,čokoládou,cukríkmi,hranolkami"},{"slug":"exercising","title":"Cvičenie","search":"cvičenie,denné cvičenie,joga,beh,fitness"},{"slug":"playing-with-friends","title":"Hranie s priateľmi","search":"hrať sa s priateľmi,ísť von s priateľmi,stretávať sa s priateľmi"},{"slug":"playing-ball","title":"Hranie lopty","search":"hrať loptu,mať 3 lopty,basketbal,futbal,futbal,volejbal"},{"slug":"painting","title":"Maľovanie","search":"maľba,umenie,plátno,skicovanie,kreslenie,maľovanie,omaľovánka"},{"slug":"hanging-out-with-family","title":"Stretnutie s rodinou","search":"stretávanie sa s rodinou,hranie sa s rodinou,rodinný čas"},{"slug":"riding-bicycle","title":"Jazda na bicykli","search":"jazda na bicykli,jazda na bicykli,bicyklovanie"},{"slug":"taking-a-ride-in-the-car","title":"Jazda v aute","search":"jazda v aute,autobus,taxi,uber"},{"slug":"swimming","title":"Plávanie","search":"plávanie,vodné športy,kúpanie,potápanie,potápanie"},{"slug":"drinking-juice","title":"Pitie šťavy","search":"pitný džús,pitná sóda,pomarančový džús,smoothie"},{"slug":"preparing-the-table","title":"Príprava stola","search":"príprava stola,prestretie stola,spôsob stolovania"},{"slug":"cleaning-glasses","title":"Čistenie okuliarov","search":"čistenie okuliarov,čistenie okuliarov"},{"slug":"shopping","title":"Nakupovanie","search":"nakupovanie,chodenie do nákupného centra,nákupného centra,nákupného centra"},{"slug":"journaling","title":"Vedenie denníka","search":"písanie denníka,denníka,kalendára"},{"slug":"praying","title":"Modliť sa","search":"modlitba,chodenie do kostola,modlitba,mešita,synagóga"},{"slug":"dancing","title":"Tancovanie","search":"tanec,hop,break dance"},{"slug":"helping-my-mother","title":"Pomoc mojej mame","search":"pomoc mojej mame,mame"},{"slug":"helping-my-father","title":"Pomoc môjmu Otcovi","search":"pomoc môjmu otcovi,otcovi"},{"slug":"practicing-instruments","title":"Cvičné nástroje","search":"nástroje na cvičenie,gitara,klavír,husle,flauta"},{"slug":"getting-dressed","title":"Obliekanie","search":"obliekanie,obliekanie,obliekanie"},{"slug":"doctors-appointment","title":"Vymenovanie lekára","search":"návšteva lekára,dátum,stretnutie,stretnutie,stretnutie"},{"slug":"talking-to-therapist","title":"Rozhovor s terapeutom","search":"rozhovor s terapeutom,chodenie na terapiu,terapia,stretnutie,schôdzka"},{"slug":"eating-out","title":"Jesť vonku","search":"jesť vonku,jesť vonku"},{"slug":"going-to-school","title":"Ísť do školy","search":"chodenie do školy,škôlky,jaslí,jaslí,denného stacionára"},{"slug":"going-to-park","title":"Ide sa do parku","search":"ísť do parku,na ihrisko,ihrisko"},{"slug":"singing","title":"Spev","search":"spev,karaoke,spievať pieseň,pieseň,hudbu"},{"slug":"going-to-cinema","title":"Ísť do kina","search":"ísť do kina,kina,divadla,pozerať film"},{"slug":"learning-code","title":"Učebný kód","search":"učenie kódu,kódovanie,počítač"},{"slug":"drinking-milk","title":"Pitné mlieko","search":"pitie mlieka,pitie"},{"slug":"playing-hopscotch","title":"Hranie Hopscotch","search":"hrať hopsctoch,hrať sa vonku,ísť sa hrať von"},{"slug":"clearing-the-table","title":"Čistenie stola","search":"upratanie stola,pomoc pri večeri,príprava večere"},{"slug":"hanging-out-with-pet","title":"Stretnutie s domácim miláčikom","search":"Stretnutie s domácim miláčikom,mačkou,psom,rybou,vtákom"},{"slug":"doing-skincare","title":"Starostlivosť o pleť","search":"starostlivosť o pleť,starostlivosť o tvár,krém na tvár,opaľovací krém"},{"slug":"visiting-relatives","title":"Príbuzní na návšteve","search":"návšteva príbuzných,babka,dedko,babka,dedko"},{"slug":"going-on-picnic","title":"Ide sa na piknik","search":"ísť na piknik,grilovanie,grilovanie,varenie vonku,grilovanie,varenie"},{"slug":"making-paper-crafts","title":"Výroba papierových remesiel","search":"výroba papierových remesiel,origami,kutilov"},{"slug":"taking-out-the-trash","title":"Vynášanie koša","search":"vynášanie smetí,smetí,smetí"},{"slug":"doing-puzzle","title":"Robiť puzzle","search":"robiť puzzle,hrať sa vo vnútri"},{"slug":"recycle","title":"Recyklovať","search":"recyklovať,odpadky,odpadky,odpadky"}]