[{"slug":"hospital-bed","title":"рж╣рж╛рж╕ржкрж╛рждрж╛рж▓рзЗрж░ ржмрж┐ржЫрж╛ржирж╛","phrases":[{"type":"ЁЯЩЛ","phrase":"ржЖржкржирж┐ ржХрж┐ ржЖржорж╛рж░ рж╣рж╛рж╕ржкрж╛рждрж╛рж▓рзЗрж░ ржмрзЗржб ржирж┐ржпрж╝рзЗ рж╕рж╛рж╣рж╛ржпрзНржп ржХрж░рждрзЗ ржкрж╛рж░рзЗржи?"}]},{"slug":"weight-loss","title":"ржУржЬржи ржХржорж╛ржирзЛ","phrases":[{"type":"ЁЯПЛя╕П","phrase":"ржЖржорж┐ ржЖржорж╛рж░ ржЦрж╛ржжрзНржп ржЧрзНрж░рж╣ржг ржкрж░рж┐ржорж┐ржд ржкрзНрж░ржпрж╝рзЛржЬржи."},{"type":"ЁЯПГтАНтЩАя╕П","phrase":"ржЖржорж┐ ржУржЬржи рж╣рж╛рж░рж╛ржЪрзНржЫрж┐."},{"type":"ЁЯей","phrase":"ржЖржорж╛рж░ ржУржЬржи ржмрж╛ржбрж╝ржЫрзЗред"}]},{"slug":"exercise","title":"ржмрзНржпрж╛ржпрж╝рж╛ржо","phrases":[{"type":"ЁЯПЛя╕П","phrase":"ржЖржорж┐ ржмрзНржпрж╛ржпрж╝рж╛ржо ржХрж░ржЫрж┐ред"},{"type":"тП▓я╕П","phrase":"ржЖржорж┐ ржПржХржЯрж┐ ржмрзНржпрж╛ржпрж╝рж╛ржо рж░рзБржЯрж┐ржи ржЖржЫрзЗ."}]},{"slug":"medical-history","title":"ржЪрж┐ржХрж┐рзОрж╕рж╛ ржЗрждрж┐рж╣рж╛рж╕","phrases":[{"type":"ЁЯУВ","phrase":"ржПржЦрж╛ржирзЗ ржЖржорж╛рж░ ржЪрж┐ржХрж┐рзОрж╕рж╛ ржЗрждрж┐рж╣рж╛рж╕."}]},{"slug":"vitamin-c","title":"ржнрж┐ржЯрж╛ржорж┐ржи рж╕рж┐","phrases":[{"type":"ЁЯН╣","phrase":"ржЖржорж╛рж░ ржнрж┐ржЯрж╛ржорж┐ржи рж╕рж┐ ржирж┐рждрзЗ рж╣ржмрзЗред"},{"type":"ЁЯНК","phrase":"ржХржорж▓рж╛рж▓рзЗржмрзБрждрзЗ рж░ржпрж╝рзЗржЫрзЗ ржнрж┐ржЯрж╛ржорж┐ржи рж╕рж┐ред"}]},{"slug":"thermometer","title":"ржерж╛рж░рзНржорзЛржорж┐ржЯрж╛рж░","phrases":[{"type":"ЁЯдТ","phrase":"ржЖржкржирж┐ ржЖржорж╛рж░ ржЬрзНржмрж░ ржкрж░рж┐ржорж╛ржк ржХрж░рждрзЗ ржкрж╛рж░рзЗржи?"},{"type":"ЁЯМбя╕П","phrase":"ржПржХржЯрж┐ ржерж╛рж░рзНржорзЛржорж┐ржЯрж╛рж░ ржХрж┐ржнрж╛ржмрзЗ ржХрж╛ржЬ ржХрж░рзЗ?"}]},{"slug":"pills","title":"ржмржбрж╝рж┐","phrases":[{"type":"ЁЯТК","phrase":"ржЖржорж╛рж░ ржмржбрж╝рж┐ ржЦрзЗрждрзЗ рж╣ржмрзЗред"},{"type":"ЁЯСЙ","phrase":"ржЖржкржирж┐ ржХрж┐ ржЖржкржирж╛рж░ ржмржбрж╝рж┐ ржЦрзЗржпрж╝рзЗржЫрзЗржи?"}]},{"slug":"medical-mask","title":"ржорзЗржбрж┐ржХрзЗрж▓ ржорж╛рж╕рзНржХ","phrases":[]},{"slug":"dental-care","title":"ржжрж╛ржБрждрзЗрж░ ржпрждрзНржи","phrases":[{"type":"ЁЯж╖","phrase":"ржЖржорж╛рж░ ржжрж╛ржБржд ржмрзНржпрж╛ржерж╛ред"},{"type":"ЁЯж╖","phrase":"ржЖржорж┐ ржЖржорж╛рж░ ржжрж╛ржБржд ржорж╛ржЬрж┐рждрзЗржЫрж┐."}]},{"slug":"hearing-exam","title":"рж╢рзБржирж╛ржирж┐рж░ ржкрж░рзАржХрзНрж╖рж╛","phrases":[{"type":"ЁЯСВ","phrase":"ржЖржорж╛рж░ рж╢рзНрж░ржмржг рж╕ржорж╕рзНржпрж╛ ржЖржЫрзЗред"},{"type":"ЁЯж╗","phrase":"ржЖржорж╛рж░ рж╢рзБржирж╛ржирж┐рж░ ржкрж░рзАржХрзНрж╖рж╛ рж╣ржмрзЗред"}]},{"slug":"hospital","title":"рж╣рж╛рж╕ржкрж╛рждрж╛рж▓","phrases":[{"type":"ЁЯПе","phrase":"ржЖржорж┐ рж╣рж╛рж╕ржкрж╛рждрж╛рж▓рзЗ ржпрж╛ржЪрзНржЫрж┐."},{"type":"ЁЯПе","phrase":"ржЖржорж┐ рж╣рж╛рж╕ржкрж╛рждрж╛рж▓рзЗ ржЖржЫрж┐ред"}]},{"slug":"stethoscope","title":"рж╕рзНржЯрзЗржерзЛрж╕рзНржХрзЛржк","phrases":[{"type":"ЁЯСитАНтЪХя╕П","phrase":"ржбрж╛ржХрзНрждрж╛рж░рж░рж╛ рж╕рзНржЯрзЗржерзЛрж╕рзНржХрзЛржк ржмрзНржпржмрж╣рж╛рж░ ржХрж░рзЗржиред"},{"type":"ЁЯй║","phrase":"ржЖржорж┐ ржХрж┐ ржЦрзЗрж▓ржирж╛ рж╕рзНржЯрзЗржерзЛрж╕рзНржХрзЛржк ржкрзЗрждрзЗ ржкрж╛рж░рж┐?"}]},{"slug":"ambulance","title":"ржЕрзНржпрж╛ржорзНржмрзБрж▓рзЗржирзНрж╕","phrases":[{"type":"ЁЯСА","phrase":"ржПржХржЯрж╛ ржЕрзНржпрж╛ржорзНржмрзБрж▓рзЗржирзНрж╕ ржжрзЗржЦрж▓рж╛ржоред"},{"type":"ЁЯСВ","phrase":"ржЖржорж┐ ржПржХржЯрж┐ ржЕрзНржпрж╛ржорзНржмрзБрж▓рзЗржирзНрж╕ рж╕рж╛ржЗрж░рзЗржи рж╢рзБржирждрзЗ."}]},{"slug":"drugstore","title":"ржУрж╖рзБржзрзЗрж░ ржжрзЛржХрж╛ржи","phrases":[{"type":"ЁЯз╛","phrase":"ржЖржорж╛рж░ ржкрзНрж░рзЗрж╕ржХрзНрж░рж┐ржкрж╢ржи ржкрзВрж░ржг ржХрж░рждрзЗ рж╣ржмрзЗред"},{"type":"тЮбя╕П","phrase":"ржПржЦрж╛ржирзЗ ржЖржорж╛рж░ ржкрзНрж░рзЗрж╕ржХрзНрж░рж┐ржкрж╢ржи."}]},{"slug":"emergency","title":"ржЬрж░рзБрж░рзА ржЕржмрж╕рзНржерж╛","phrases":[{"type":"ЁЯЪи","phrase":"ржЖржорж╛рж░ ржПржХржЯрж┐ рж╕рзНржмрж╛рж╕рзНржерзНржп ржЬрж░рзБрж░рзА ржЕржмрж╕рзНржерж╛ ржЖржЫрзЗред"},{"type":"ЁЯЪС","phrase":"ржЖржорж┐ ржЬрж░рзБрж░рзА рж░рзБржорзЗ ржпрж╛ржЪрзНржЫрж┐."}]},{"slug":"health-insurance","title":"рж╕рзНржмрж╛рж╕рзНржерзНржп ржмрзАржорж╛","phrases":[{"type":"тЪХя╕П","phrase":"ржЖржорж╛рж░ рж╕рзНржмрж╛рж╕рзНржерзНржп ржмрзАржорж╛ ржЖржЫрзЗред"},{"type":"тЭМ","phrase":"ржЖржорж╛рж░ рж╕рзНржмрж╛рж╕рзНржерзНржп ржмрзАржорж╛ ржирзЗржЗред"}]},{"slug":"doctor","title":"ржбрж╛ржХрзНрждрж╛рж░","phrases":[{"type":"тЭдя╕П","phrase":"ржЖржорж┐ ржЖржорж╛рж░ ржбрж╛ржХрзНрждрж╛рж░ ржкржЫржирзНржж."},{"type":"ЁЯдй","phrase":"ржбрж╛ржХрзНрждрж╛рж░ ржЖржорж╛ржХрзЗ рж╕рж╛рж╣рж╛ржпрзНржп ржХрж░ржЫрзЗржиред"}]},{"slug":"nurse","title":"ржирж╛рж░рзНрж╕","phrases":[{"type":"тЭдя╕П","phrase":"ржЖржорж┐ ржЖржорж╛рж░ ржирж╛рж░рзНрж╕ ржкржЫржирзНржж."},{"type":"ЁЯдй","phrase":"ржирж╛рж░рзНрж╕ ржЖржорж╛ржХрзЗ рж╕рж╛рж╣рж╛ржпрзНржп ржХрж░ржЫрзЗред"}]}]