[{"slug":"practicing-speaking","title":"Практика разговорной речи","search":"практиковать разговор,говорить,говорить,говорить,говорить"},{"slug":"using-assistive-cards","title":"Использование вспомогательных карточек","search":"использование вспомогательных карт,пример,разговор,терапия,предложение"},{"slug":"planning-the-day","title":"Планирование дня","search":"планирование дня с помощью wingo,календаря,ежедневного планирования"},{"slug":"sleeping","title":"Спать","search":"сон,время сна,сон,сновидение,кошачий сон,сон,отдых"},{"slug":"waking-up","title":"Просыпаться","search":"просыпаться,пробуждение,вставать,доброе утро"},{"slug":"relaxing","title":"расслабляться","search":"расслабиться,вздремнуть,успокоиться,лечь"},{"slug":"doing-homework","title":"Уроки делаю","search":"делать домашнее задание,учиться,выполнять обязанности,заниматься,самообучаться"},{"slug":"reading-book","title":"Читая книгу","search":"чтение книг,журналов,чтение комиксов,чтение манги"},{"slug":"doing-outside-activities","title":"Занятия на свежем воздухе","search":"занятия на свежем воздухе,бег,походы,прогулки,солнечные ванны,скалолазание,кемпинг"},{"slug":"studying-mathematics","title":"Изучение математики","search":"изучение математики,обучение,математическая гимнастика,курс математики"},{"slug":"brushing-teeth","title":"Чистить зубы","search":"чистка зубов,зубная щетка,подготовка ко сну,стерилизация,полоскание рта"},{"slug":"preparing-school-bag","title":"Подготовка школьной сумки","search":"подготовка школьной сумки,подготовка к школе,коробка для завтрака"},{"slug":"taking-a-bath","title":"Принимая ванну","search":"принимать ванну,душ,ванну,принимать душ"},{"slug":"having-breakfast","title":"Завтракать","search":"завтракать,ранний прием пищи,поздний завтрак,утренний прием пищи,прием пищи"},{"slug":"listening-to-music","title":"Слушать музыку","search":"слушать музыку,пользоваться телефоном,смартфоном,звонить"},{"slug":"having-dinner","title":"Ужин","search":"ужинать,обедать,есть,ужинать"},{"slug":"playing-with-toys","title":"Игра с игрушками","search":"игра с игрушками,барби,машинки"},{"slug":"playing-video-games","title":"Играя в видео игры","search":"играю в видеоигры,xbox,playstation,nintendo,fortnite,компьютерная игра,консольная игра,minecraft,roblox"},{"slug":"tidy-room","title":"Чистая комната","search":"уборка,уборка,уборка"},{"slug":"watching-tv","title":"Смотря телевизор","search":"смотреть тв,телевидение,сериалы,смотреть кино,документальный,смотреть мультфильм,аниме"},{"slug":"having-snacks","title":"Закуски","search":"закуски,нездоровая пища,шоколад,конфеты,чипсы"},{"slug":"exercising","title":"Упражнения","search":"упражнения,ежедневные тренировки,йога,бег,фитнес"},{"slug":"playing-with-friends","title":"Игра с друзьями","search":"играть с друзьями,гулять с друзьями,гулять с друзьями"},{"slug":"playing-ball","title":"Игра в мяч","search":"играть в мяч,есть 3 мяча,баскетбол,футбол,футбол,волейбол"},{"slug":"painting","title":"Картина","search":"живопись,искусство,холст,рисование,рисование,раскраска,книжка-раскраска"},{"slug":"hanging-out-with-family","title":"Прогулки с семьей","search":"тусоваться с семьей,играть с семьей,проводить время с семьей"},{"slug":"riding-bicycle","title":"Кататься на велосипеде","search":"кататься на велосипеде,кататься на велосипеде,кататься на велосипеде"},{"slug":"taking-a-ride-in-the-car","title":"Поездка в машине","search":"покататься на машине,на автобусе,такси,убере"},{"slug":"swimming","title":"Плавание","search":"плавание,водные виды спорта,искупаться,дайвинг,погружение"},{"slug":"drinking-juice","title":"Питьевой сок","search":"пить сок,питьевая сода,апельсиновый сок,коктейль"},{"slug":"preparing-the-table","title":"Подготовка таблицы","search":"подготовка стола,сервировка стола,правила поведения за столом"},{"slug":"cleaning-glasses","title":"Чистка очков","search":"чистка очков,чистка очков"},{"slug":"shopping","title":"Покупка","search":"шоппинг,поход в торговый центр,торговый центр,торговый центр"},{"slug":"journaling","title":"Ведение журнала","search":"ведение дневника,дневник,календарь"},{"slug":"praying","title":"молиться","search":"молиться,ходить в церковь,молитву,мечеть,синагогу"},{"slug":"dancing","title":"Танцы","search":"танцы,хоп,брейк-данс"},{"slug":"helping-my-mother","title":"Помогая моей маме","search":"помогаю маме,мама"},{"slug":"helping-my-father","title":"Помогая моему отцу","search":"помогая моему отцу,отец"},{"slug":"practicing-instruments","title":"Практические инструменты","search":"Упражнения на музыкальных инструментах,гитаре,фортепиано,скрипке,флейте"},{"slug":"getting-dressed","title":"Одеваться","search":"одеваться,одеваться,одеваться"},{"slug":"doctors-appointment","title":"Прием у доктора","search":"прием к врачу,свидание,встреча,назначение,рандеву"},{"slug":"talking-to-therapist","title":"Разговор с терапевтом","search":"разговор с терапевтом,посещение терапии,терапия,встреча,назначение"},{"slug":"eating-out","title":"Еда вне дома","search":"есть вне дома,есть вне дома"},{"slug":"going-to-school","title":"Ходить в школу","search":"ходить в школу,детский сад,ясли,детский сад"},{"slug":"going-to-park","title":"Идти в парк","search":"собираемся в парк,на детскую площадку,в игровую зону"},{"slug":"singing","title":"Пение","search":"пение,караоке,спеть песню,песню,музыку"},{"slug":"going-to-cinema","title":"Поход в кино","search":"ходить в кино,кино,театр,смотреть кино"},{"slug":"learning-code","title":"Код обучения","search":"код обучения,кодирование,компьютер"},{"slug":"drinking-milk","title":"Питьевое молоко","search":"пить молоко,пить"},{"slug":"playing-hopscotch","title":"Игра в классики","search":"играть в hopsctoch,играть на улице,выходить на улицу играть"},{"slug":"clearing-the-table","title":"Очистка стола","search":"уборка со стола,помощь на ужин,приготовление ужина"},{"slug":"hanging-out-with-pet","title":"тусоваться с домашним животным","search":"гулять с домашним животным,кошкой,собакой,рыбой,птицей"},{"slug":"doing-skincare","title":"Уход за кожей","search":"уход за кожей,уход за лицом,крем для лица,солнцезащитный крем"},{"slug":"visiting-relatives","title":"Посещение родственников","search":"в гостях у родственников,бабушки,дедушки,бабушки,дедушки"},{"slug":"going-on-picnic","title":"Собираюсь на пикник","search":"пикник,барбекю,гриль,приготовление пищи на улице,барбекю,приготовление пищи"},{"slug":"making-paper-crafts","title":"Изготовление бумажных поделок","search":"изготовление поделок из бумаги,оригами,сделай сам"},{"slug":"taking-out-the-trash","title":"Выносить мусор","search":"вынос мусора,мусора,хлама"},{"slug":"doing-puzzle","title":"Делать головоломки","search":"делать головоломки,играть внутри"},{"slug":"recycle","title":"Перерабатывать","search":"перерабатывать,мусор,мусор,хлам"}]