[{"slug":"walking","title":"المشي","search":"المشي والجري"},{"slug":"cooking-food","title":"طهي الطعام","search":"الطبخ والتحضير"},{"slug":"using-phone","title":"باستخدام الهاتف","search":"باستخدام الهاتف ، الهاتف الذكي ، الاتصال"},{"slug":"practicing-speaking","title":"ممارسة التحدث","search":"التدرب على التحدث والتحدث والتحدث وأداء الكلام والكلام"},{"slug":"waking-up","title":"الاستيقاظ","search":"الاستيقاظ ، الاستيقاظ ، الاستيقاظ ،"},{"slug":"sleeping","title":"نائم","search":"النوم ، وقت النوم ، الاسترخاء ، الحلم ، القيلولة ، القيلولة ، الراحة"},{"slug":"relax","title":"يستريح","search":"ريالكس ، قيلولة ، مهدئة ، استلق"},{"slug":"doing-homework","title":"القيام بالواجب المنزلي","search":"القيام بالواجبات المنزلية والدراسة والواجب والممارسة"},{"slug":"reading-book","title":"قراءة كتاب","search":"قراءة الكتب والمجلات"},{"slug":"doing-homework","title":"القيام بالواجب المنزلي","search":"القيام بالواجبات المنزلية والدراسة والواجب والممارسة"},{"slug":"studying-mathematics","title":"دراسة الرياضيات","search":"دراسة الرياضيات ، التعلم ، ممارسة الرياضيات ، الرياضيات بالطبع"},{"slug":"brushing-teeth","title":"تنظيف الاسنان","search":"تفريش الأسنان ، فرشاة الأسنان ، الاستعداد للنوم ، التعقيم ، غسول الفم"},{"slug":"going-to-school","title":"الذهاب إلى المدرسة","search":"الذهاب إلى المدرسة ، الانتقال إلى المدرسة ، الحضانة ، الحضانة ، الحضانة"},{"slug":"taking-a-bath","title":"أخذ حمام","search":"أخذ حمام ، دش ، حوض الاستحمام ، الاستحمام ، lav"},{"slug":"having-breakfast","title":"أتناول طعام الفطور","search":"تناول الفطور ، الوجبة المبكرة ، الفطور المتأخر ، وجبة الصباح ، تناول الطعام"},{"slug":"listening-to-music","title":"اسمع اغاني","search":"الاستماع إلى الموسيقى ، باستخدام الهاتف ، والهاتف الذكي ، والاتصال"},{"slug":"having-dinner","title":"تناول العشاء","search":"تناول العشاء ، ووجبة العشاء ، والعيد ، وتناول العشاء"},{"slug":"playing-with-toys","title":"يلعب بالدمي","search":"يلعب بالدمي،"},{"slug":"playing-video-games","title":"العب العاب الفيديو","search":"لعب ألعاب الفيديو ، إكس بوكس ، بلاي ستيشن ، نينتندو ، فورتنايت ، لعبة كمبيوتر"},{"slug":"tidy-room","title":"غرفة مرتبة","search":"غرفة الترتيب ، غرفة التنظيف ، غرفة التنوب"},{"slug":"watching-tv","title":"مشاهدة التلفزيون","search":"مشاهدة التلفزيون والتلفزيون والمسلسلات والفيلم الوثائقي"},{"slug":"having-snacks","title":"تناول وجبات خفيفة","search":"تناول الوجبات الخفيفة والوجبات السريعة والحلويات"},{"slug":"exercising","title":"ممارسة","search":"ممارسة التمارين اليومية واليوجا"},{"slug":"playing-ball","title":"لعب الكرة","search":"لعب الكرة ، لديك 3 كرات ، كرة السلة ، كرة القدم ، كرة القدم ، الكرة الطائرة"},{"slug":"playing-with-friends","title":"اللعب مع الأصدقاء","search":"اللعب مع الأصدقاء ، الخروج مع الأصدقاء ، التسكع مع الأصدقاء"},{"slug":"painting","title":"تلوين","search":"الرسم والفن والقماش والرسم"},{"slug":"hanging-out-with-family","title":"التسكع مع العائلة","search":"التسكع مع العائلة واللعب مع العائلة"},{"slug":"cycling","title":"ركوب الدراجات","search":"ركوب الدراجات ، وركوب الدواسة ، وركوب الدراجة"},{"slug":"taking-a-ride-in-the-car","title":"أخذ جولة في السيارة","search":"أخذ جولة في السيارة ، وركوب الحافلة"},{"slug":"swimming","title":"سباحة","search":"السباحة والرياضات المائية والسباحة"},{"slug":"drinking-juice","title":"يشرب عصير","search":"شرب العصير وشرب الصودا"},{"slug":"preparing-the-table","title":"تحضير الجدول","search":"تحضير الطاولة ، وضع الطاولة ،"},{"slug":"cleaning-glasses","title":"نظارات التنظيف","search":"أكواب التنظيف ، كوب التنظيف ، كوب التنظيف"},{"slug":"shopping","title":"التسوق","search":"التسوق ، الذهاب إلى المركز التجاري"},{"slug":"praying","title":"يدعو","search":"الصلاة ، الذهاب إلى الكنيسة ،"},{"slug":"dancing","title":"الرقص","search":"الرقص ، قفز"},{"slug":"helping-my-mother","title":"مساعدة أمي","search":"أساعد أمي ، أمي"},{"slug":"helping-my-father","title":"مساعدة والدي","search":"مساعدة والدي"},{"slug":"practicing-instruments","title":"ممارسة الأدوات","search":"العزف على الآلات ، الجيتار ، البيانو ، الكمان ، الفلوت"},{"slug":"getting-dressed","title":"أرتدي ملابسي","search":"أرتدي ملابسي"},{"slug":"doctors-appointment","title":"موعد طبيب","search":"موعد الطبيب ، موعده ، موعده"},{"slug":"talking-to-therapist","title":"التحدث إلى المعالج","search":"التحدث إلى المعالج"},{"slug":"eating-out","title":"ياكل بالخارج","search":"تناول الطعام بالخارج ، تناول الطعام بالخارج"},{"slug":"going-to-the-park","title":"الذهاب الى الحديقة","search":"الذهاب إلى الحديقة ، الملعب ، منطقة اللعب"}]